ipymongodb/__init__.py
ipymongodb/collection.py
ipymongodb/database.py
ipymongodb_test/__init__.py
ipymongodb_test/_testenv.py
ipymongodb_test/utest.py
ipymongodb-0.5.0.dist-info/LICENSE
ipymongodb-0.5.0.dist-info/METADATA
ipymongodb-0.5.0.dist-info/WHEEL
ipymongodb-0.5.0.dist-info/top_level.txt
ipymongodb-0.5.0.dist-info/RECORD
